{
  "pageType":"function",
  "title":"CacheGetProperties",
  "name":"CacheGetProperties",
  "memberName":"",
  "description":"Gets the cache properties for the object cache, the page cache, or both. The information is application-specific.",
  "status":"",
  "deprecated":false,
  "class":"lucee.runtime.functions.cache.CacheGetProperties",
  "returnType":"array",
  "argumentType":"",
  "keywords":[
    
  ],
  "arguments":[
    {
      "name":"type",
      "description":"define which cache instances information are returned\n- \"\" or not set - information to all default caches (object,template,resource,query)\n- \"object\" - information to  \"Default Object\" Cache\n- \"template\" - information to  \"Default Template\" Cache\n- \"query\" - information to  \"Default Query\" Cache\n- \"resource\" - information to  \"Default Resource\" Cache\n- {cache name} - information to  a specific cache ",
      "type":"string",
      "required":false,
      "default":""
    }
  ],
  "examples":[
    
  ],
  "history":[
    
  ]
}