{
  "pageType":"function",
  "title":"binaryEncode",
  "name":"binaryEncode",
  "memberName":"",
  "description":"Converts binary data to a string.",
  "status":"",
  "deprecated":false,
  "class":"lucee.runtime.functions.conversion.BinaryEncode",
  "returnType":"string",
  "argumentType":"",
  "keywords":[
    "binary"
  ],
  "arguments":[
    {
      "name":"binary",
      "description":"A variable containing the binary data to encode.",
      "type":"binary",
      "required":true,
      "default":""
    },
    {
      "name":"encoding",
      "description":"A string that specifies the encoding method to use to represent the data; one of the following:\n- Hex: use the characters 0-9 and A-F to represent the hexadecimal value of each byte.\n- UU: use the UNIX UUencode algorithm to convert the data\n- Base64: use the Base64 algorithm to convert the data, as specified by IETF RFC 2045, at www.ietf.org/rfc/rfc2045.txt.",
      "type":"string",
      "required":true,
      "default":""
    }
  ],
  "examples":[
    
  ],
  "history":[
    
  ]
}