{
  "pageType":"function",
  "title":"arrayFirst",
  "name":"arrayFirst",
  "memberName":"first",
  "description":"Returns the first item from an array. Throws an error if the array is empty.",
  "status":"",
  "deprecated":false,
  "class":"lucee.runtime.functions.arrays.ArrayFirst",
  "returnType":"any",
  "argumentType":"",
  "keywords":[
    "array"
  ],
  "arguments":[
    {
      "name":"array",
      "description":"The array to obtain the first Item from",
      "type":"array",
      "required":true,
      "default":""
    }
  ],
  "examples":[
    
  ],
  "history":[
    
  ]
}